
.source Small.jasm
.class public Small
.super java/lang/Object

; standard class initializer
.method public <init>()V
	aload_0
	invokenonvirtual java/lang/Object/<init>()V
	return
.end method

.method public static main([Ljava/lang/String;)V
	.limit locals 2
	.limit stack 18


	; 'start' of generated code

	ldc 0
	istore 0
	ldc 0
	istore 1
	ldc 10
	istore 1
	iload 1

	; pop 1 value from the stack for cleaning up dsb cleanup start
	pop
	ldc 0
	istore 0
	iload 0

	; pop 1 value from the stack for cleaning up dsb cleanup start
	pop


WHILE0:
	; loading of a variable/constant
	iload 0

	; loading of a variable/constant
	iload 1

	; less-than statement
	if_icmplt LabelLT1
	iconst_0
	goto LabelLT2

LabelLT1:
	iconst_1

LabelLT2:
	ifeq ENDWHILE0

	; loading of a variable/constant
	iload 0
	dup

	; push reference to system.out on stack
	getstatic java/lang/System/out Ljava/io/PrintStream;
	swap

	; print the output
	invokevirtual java/io/PrintStream/println(I)V

	ldc 1
	iadd
	istore 0
	iload 0

	; pop 1 value from the stack for cleaning up exprdo cleanup
	pop
	goto WHILE0

ENDWHILE0:
	ldc 100
	dup
	i2c
	invokestatic java/lang/String/valueOf(C)Ljava/lang/String;

	; push reference to system.out on stack
	getstatic java/lang/System/out Ljava/io/PrintStream;
	swap

	; print the output
	invokevirtual java/io/PrintStream/println(Ljava/lang/String;)V

	ldc 111
	dup
	i2c
	invokestatic java/lang/String/valueOf(C)Ljava/lang/String;

	; push reference to system.out on stack
	getstatic java/lang/System/out Ljava/io/PrintStream;
	swap

	; print the output
	invokevirtual java/io/PrintStream/println(Ljava/lang/String;)V


	; pop 2 values from the stack for cleaning up print
	pop
	pop
	ldc 110
	dup
	i2c
	invokestatic java/lang/String/valueOf(C)Ljava/lang/String;

	; push reference to system.out on stack
	getstatic java/lang/System/out Ljava/io/PrintStream;
	swap

	; print the output
	invokevirtual java/io/PrintStream/println(Ljava/lang/String;)V


	; pop 1 value from the stack for cleaning up print
	pop
	ldc 101
	dup
	i2c
	invokestatic java/lang/String/valueOf(C)Ljava/lang/String;

	; push reference to system.out on stack
	getstatic java/lang/System/out Ljava/io/PrintStream;
	swap

	; print the output
	invokevirtual java/io/PrintStream/println(Ljava/lang/String;)V


	; pop 1 value from the stack for cleaning up print
	pop


	; 'end' of generated code
	return
.end method
