
.source Small2_read.jasm
.class public Small2_read
.super java/lang/Object

; standard class initializer
.method public <init>()V
	aload_0
	invokenonvirtual java/lang/Object/<init>()V
	return
.end method

.method public static main([Ljava/lang/String;)V
	.limit locals 2
	.limit stack 25


	; 'start' of generated code

	ldc 0
	istore 0
	invokestatic Small2_read.readint()I
	istore 0
	iload 0

	; pop 1 value from the stack for cleaning up dsb cleanup start
	pop

	; loading of a variable/constant
	iload 0
	ldc 100
	iadd
	istore 0
	iload 0

	; pop 1 value from the stack for cleaning up dsb cleanup start
	pop
	ldc 0
	istore 1
	ldc 3
	istore 1
	iload 1

	; pop 1 value from the stack for cleaning up dsb cleanup start
	pop

	; loading of a variable/constant
	iload 1
	ldc 1
	iadd
	istore 1
	iload 1

	; pop 1 value from the stack for cleaning up dsb cleanup start
	pop


WHILE0:
	; loading of a variable/constant
	iload 1
	ldc 10

	; less-equals statement
	if_icmple LabelLE1
	iconst_0
	goto LabelLE2

LabelLE1:
	iconst_1

LabelLE2:
	ifeq ENDWHILE0

	; loading of a variable/constant
	iload 1
	ldc 2
	iadd
	istore 1
	iload 1

	; pop 1 value from the stack for cleaning up exprdo cleanup
	pop
	goto WHILE0


ENDWHILE0:
	; loading of a variable/constant
	iload 1
	dup

	; push reference to system.out on stack
	getstatic java/lang/System/out Ljava/io/PrintStream;
	swap

	; print the output
	invokevirtual java/io/PrintStream/println(I)V


	; pop 1 value from the stack for cleaning up dsb cleanup start
	pop

	; loading of a variable/constant
	iload 0

	; loading of a variable/constant
	iload 1
	imul
	istore 0
	iload 0

	; pop 1 value from the stack for cleaning up dsb cleanup start
	pop

	; loading of a variable/constant
	iload 1
	dup

	; push reference to system.out on stack
	getstatic java/lang/System/out Ljava/io/PrintStream;
	swap

	; print the output
	invokevirtual java/io/PrintStream/println(I)V


	; loading of a variable/constant
	iload 1
	dup

	; push reference to system.out on stack
	getstatic java/lang/System/out Ljava/io/PrintStream;
	swap

	; print the output
	invokevirtual java/io/PrintStream/println(I)V


	; pop 2 values from the stack for cleaning up print
	pop
	pop

	; loading of a variable/constant
	iload 0
	dup

	; push reference to system.out on stack
	getstatic java/lang/System/out Ljava/io/PrintStream;
	swap

	; print the output
	invokevirtual java/io/PrintStream/println(I)V


	; pop 1 value from the stack for cleaning up dsb cleanup start
	pop


	; 'end' of generated code
	return
.end method
	
; int readint() function
.method public static readint()I
	.limit locals 2
	.limit stack 10
	ldc 0
	istore 0

LabelRead0:
	getstatic java/lang/System/in Ljava/io/InputStream;
	invokevirtual java/io/InputStream/read()I
	istore 1
	iload 1
	ldc 10
	isub
	ifeq LabelRead1
	iload 1
	ldc 13
	isub
	ifeq LabelRead1
	iload 1
	ldc 32
	isub
	ifeq LabelRead1
	iload 1
	ldc 48
	isub
	ldc 10
	iload 0
	imul
	iadd
	istore 0
	goto LabelRead0

LabelRead1:
	; local variable 0 holds the read integer
	iload 0
	ireturn
	
.end method
